{
    "5.366": [
        "ChoppingBoard",
        "WoodenFork",
        "Mango_A"
    ],
    "11.831": [
        "MuffinPan",
        "BlackCeramicMug",
        "BambooPlate"
    ],
    "19.197": [
        "KitchenKnife",
        "WoodenSpoon",
        "AirPurifier_1"
    ],
    "24.863": [
        "MuffinPan",
        "Pestel",
        "ChoppingBoard"
    ],
    "29.329": [
        "WhiteFlatwareTray",
        "Jam_Anon",
        "BambooPlate"
    ],
    "33.295": [
        "WoodenBowl",
        "Mango_A",
        "BlackCeramicBowl"
    ],
    "38.627": [
        "WoodenSpoon",
        "Jam_Anon",
        "WhiteFlatwareTray"
    ],
    "42.726": [
        "ChoppingBoard",
        "KitchenKnife",
        "MuffinPan"
    ],
    "48.292": [
        "BlackRoundTable",
        "DvdRemote_1",
        "TvRemote_1"
    ],
    "56.491": [
        "BlackCeramicBowl",
        "ExtendableTable",
        "CakeMocha_A"
    ],
    "61.89": [
        "Tomato_A",
        "BlackCeramicBowl",
        "Flask"
    ],
    "69.855": [
        "CandlePattern04_1",
        "CandlePattern03_1",
        "DvdRemote_1"
    ],
    "78.621": [
        "CoffeeCanisterLarge",
        "WhiteUtensilTray",
        "BlackCeramicMug"
    ],
    "83.453": [
        "BambooPlate",
        "WoodenSpoon",
        "MuffinPan"
    ],
    "88.053": [
        "Donut_B",
        "GreenApple_A",
        "BlackCeramicBowl"
    ]
}